unique_defaults.py
unique_defaults-1.0.dist-info/LICENSE
unique_defaults-1.0.dist-info/WHEEL
unique_defaults-1.0.dist-info/METADATA
unique_defaults-1.0.dist-info/RECORD
