Metadata-Version: 2.1
Name: unique_defaults
Version: 1.0
Summary: Replace a function's default values with objects unique to each function call
Keywords: decorator,defaults,keywords
Author-email: Jeremiah Paige <ucodery@gmail.com>
Classifier: License :: OSI Approved :: MIT License
Requires-Dist: flit ; extra == "dev"
Requires-Dist: nox ; extra == "dev"
Requires-Dist: pytest >=2.7.3 ; extra == "test"
Requires-Dist: mktestdocs ~= 0.1 ; extra == "test"
Project-URL: Home, https://github.com/ucodery/unique_defaults
Provides-Extra: dev
Provides-Extra: test
